resample.cpython-311-x86_64-linux-musl.so
cars_resample-0.1.2.dist-info/LICENSE
cars_resample-0.1.2.dist-info/WHEEL
cars_resample-0.1.2.dist-info/METADATA
cars_resample-0.1.2.dist-info/top_level.txt
cars_resample-0.1.2.dist-info/RECORD
tests/__init__.py
tests/test_cars_grid_resample.py
cars_resample.libs/libstdc++-0d31ccbe.so.6.0.32
cars_resample.libs/libgcc_s-a0b57c20.so.1
cars_resample/__init__.py
